odoo/addons/ssi_receivable_follow_up/README.rst
odoo/addons/ssi_receivable_follow_up/__init__.py
odoo/addons/ssi_receivable_follow_up/__manifest__.py
odoo/addons/ssi_receivable_follow_up/data/approval_template_data.xml
odoo/addons/ssi_receivable_follow_up/data/ir_sequence_data.xml
odoo/addons/ssi_receivable_follow_up/data/policy_template_data.xml
odoo/addons/ssi_receivable_follow_up/data/sequence_template_data.xml
odoo/addons/ssi_receivable_follow_up/models/__init__.py
odoo/addons/ssi_receivable_follow_up/models/receivable_follow_up.py
odoo/addons/ssi_receivable_follow_up/models/receivable_follow_up_detail.py
odoo/addons/ssi_receivable_follow_up/models/receivable_follow_up_type.py
odoo/addons/ssi_receivable_follow_up/models/res_partner.py
odoo/addons/ssi_receivable_follow_up/security/ir.model.access.csv
odoo/addons/ssi_receivable_follow_up/security/ir_module_category_data.xml
odoo/addons/ssi_receivable_follow_up/security/ir_rule_data.xml
odoo/addons/ssi_receivable_follow_up/security/res_group_data.xml
odoo/addons/ssi_receivable_follow_up/static/description/icon.png
odoo/addons/ssi_receivable_follow_up/views/receivable_follow_up_type_view.xml
odoo/addons/ssi_receivable_follow_up/views/receivable_follow_up_view.xml
odoo/addons/ssi_receivable_follow_up/views/res_partner_views.xml
odoo14_addon_ssi_receivable_follow_up-14.0.1.0.2.dev1.dist-info/METADATA
odoo14_addon_ssi_receivable_follow_up-14.0.1.0.2.dev1.dist-info/WHEEL
odoo14_addon_ssi_receivable_follow_up-14.0.1.0.2.dev1.dist-info/top_level.txt
odoo14_addon_ssi_receivable_follow_up-14.0.1.0.2.dev1.dist-info/RECORD
